{
    "server_url": "https://cs5.salesforce.com/services/Soap/u/5.0/00DO0000000X92w", 
    "X-SFDC-Session": "00DO0000000X92w!AR4AQAcbDmVqMdsBBb2a76EMzgQoTkeLtoS6Ne2dEkgsnOFgPqjqvRsJIhEfz_G_D1keYMS.mVN_moEQOmZlCcvjuH0wounc", 
    "project name": "BPlusDev", 
    "headers": {
        "Authorization": "OAuth 00DO0000000X92w!AR4AQAcbDmVqMdsBBb2a76EMzgQoTkeLtoS6Ne2dEkgsnOFgPqjqvRsJIhEfz_G_D1keYMS.mVN_moEQOmZlCcvjuH0wounc", 
        "Content-Type": "application/json; charset=UTF-8", 
        "Accept": "application/json"
    }, 
    "success": true, 
    "partner_url": "https://cs5.salesforce.com/services/Soap/u/35.0", 
    "apex_url": "https://cs5.salesforce.com/services/Soap/s/35.0", 
    "instance_url": "https://cs5.salesforce.com", 
    "session_id": "00DO0000000X92w!AR4AQAcbDmVqMdsBBb2a76EMzgQoTkeLtoS6Ne2dEkgsnOFgPqjqvRsJIhEfz_G_D1keYMS.mVN_moEQOmZlCcvjuH0wounc", 
    "metadata_url": "https://cs5.salesforce.com/services/Soap/m/35.0", 
    "user_id": "005900000039xb0AAA", 
    "time_stamp": "2016-01-06 11:56:59", 
    "rest_url": "https://cs5.salesforce.com/services/data/v35.0"
}